prism_logger/__init__.py
prism_logger/logger.py
prism_logger-0.1.1.dist-info/licenses/LICENSE
prism_logger-0.1.1.dist-info/METADATA
prism_logger-0.1.1.dist-info/WHEEL
prism_logger-0.1.1.dist-info/top_level.txt
prism_logger-0.1.1.dist-info/RECORD
